foxypack_youtube_pytubefix/__init__.py
foxypack_youtube_pytubefix/answers.py
foxypack_youtube_pytubefix/entities.py
foxypack_youtube_pytubefix/foxyanalysis.py
foxypack_youtube_pytubefix/foxystat.py
foxypack_youtube_pytubefix/py.typed
foxypack_youtube_pytubefix-0.0.6.dist-info/licenses/LICENSE
foxypack_youtube_pytubefix-0.0.6.dist-info/METADATA
foxypack_youtube_pytubefix-0.0.6.dist-info/WHEEL
foxypack_youtube_pytubefix-0.0.6.dist-info/top_level.txt
foxypack_youtube_pytubefix-0.0.6.dist-info/RECORD
